osinter/__main__.py
osint_comp-0.2.3.dist-info/METADATA
osint_comp-0.2.3.dist-info/WHEEL
osint_comp-0.2.3.dist-info/entry_points.txt
osint_comp-0.2.3.dist-info/top_level.txt
osint_comp-0.2.3.dist-info/RECORD
