Metadata-Version: 2.1
Name: osint-comp
Version: 0.2.3
Summary: A place to keep osint files. Mainly a personal project.
Requires-Dist: rich-click
